jr_portal_gun/__init__.py
jr_portal_gun/main.py
jr_portal_gun-0.1.0.dist-info/METADATA
jr_portal_gun-0.1.0.dist-info/WHEEL
jr_portal_gun-0.1.0.dist-info/entry_points.txt
jr_portal_gun-0.1.0.dist-info/RECORD
