Metadata-Version: 2.1
Name: jr-portal-gun
Version: 0.1.0
Summary: 
Author: Jorge Roldan
Author-email: roldanjrgl@gmail.com
Requires-Python: >=3.11,<4.0
Classifier: Programming Language :: Python :: 3
Classifier: Programming Language :: Python :: 3.11
Classifier: Programming Language :: Python :: 3.12
Classifier: Programming Language :: Python :: 3.13
Requires-Dist: typer (>=0.13.0,<0.14.0)
